MANIFEST.in
README.rst
setup.py
django_staticblog.egg-info/PKG-INFO
django_staticblog.egg-info/SOURCES.txt
django_staticblog.egg-info/dependency_links.txt
django_staticblog.egg-info/not-zip-safe
django_staticblog.egg-info/requires.txt
django_staticblog.egg-info/top_level.txt
staticblog/__init__.py
staticblog/app_settings.py
staticblog/tests.py
staticblog/urls.py
staticblog/views.py
staticblog/management/__init__.py
staticblog/management/commands/__init__.py
staticblog/management/commands/import_tumblr.py
staticblog/management/commands/update_blog.py
staticblog/templates/staticblog/archive.html
staticblog/templates/staticblog/post.html