Metadata-Version: 1.0
Name: django-staticblog
Version: 0.2.5
Summary: Markdown-based blog engine that compiles to static html pages
Home-page: http://github.com/cgrice/django-staticblog/
Author: Chris Grice
Author-email: chris@chrisgrice.com
License: MIT
Platform: UNKNOWN
Classifier: Development Status :: 3 - Alpha
Classifier: Environment :: Web Environment
Classifier: Intended Audience :: Developers
Classifier: License :: OSI Approved :: MIT License
Classifier: Operating System :: OS Independent
Classifier: Programming Language :: Python
Classifier: Framework :: Django
